src/__init__.py
src/__main__.py
src/config.py
src/exceptions.py
src/list.py
src/main.py
src/prune.py
git_prune_merged-0.4.6.dist-info/LICENSE
git_prune_merged-0.4.6.dist-info/METADATA
git_prune_merged-0.4.6.dist-info/WHEEL
git_prune_merged-0.4.6.dist-info/entry_points.txt
git_prune_merged-0.4.6.dist-info/top_level.txt
git_prune_merged-0.4.6.dist-info/RECORD
