Metadata-Version: 2.1
Name: git-prune-merged
Version: 0.4.6
Summary: A git plugin to prune local and remote branches
Home-page: https://github.com/aesteve-rh/git-prune-merged
Author: Albert Esteve
Author-email: aesteve@redhat.com
Classifier: Programming Language :: Python :: 3.10
Classifier: License :: OSI Approved :: GNU General Public License v3 (GPLv3)
License-File: LICENSE
Requires-Dist: Click
Requires-Dist: gitpython (>3.1)
Requires-Dist: pygithub (>=1.55)
Requires-Dist: pyyaml (>=6.0)
Requires-Dist: python-dateutil
